rowantree/common/sdk/__init__.py
rowantree/common/sdk/config/__init__.py
rowantree/common/sdk/config/environment.py
rowantree/common/sdk/config/environment_variable_not_found_error.py
rowantree.common.sdk-1.0.0.dist-info/LICENSE
rowantree.common.sdk-1.0.0.dist-info/METADATA
rowantree.common.sdk-1.0.0.dist-info/WHEEL
rowantree.common.sdk-1.0.0.dist-info/top_level.txt
rowantree.common.sdk-1.0.0.dist-info/RECORD
