Metadata-Version: 2.1
Name: rowantree.common.sdk
Version: 1.0.0
Summary: The Rowan Tree Common Utilities
Author: Joshua C. Burt
Author-email: joshburt@shapeandshare.com
License: MIT
Requires-Python: >=3.9
License-File: LICENSE
